LICENSE
MANIFEST.in
README.md
setup.py
doit/__init__.py
doit/command.py
doit/storage.py
doit_tasks.egg-info/PKG-INFO
doit_tasks.egg-info/SOURCES.txt
doit_tasks.egg-info/dependency_links.txt
doit_tasks.egg-info/entry_points.txt
doit_tasks.egg-info/requires.txt
doit_tasks.egg-info/top_level.txt