Metadata-Version: 1.1
Name: doit-tasks
Version: 0.1.1
Summary: Tasks on the command line
Home-page: UNKNOWN
Author: Josef Lange
Author-email: josef.d.lange@me.com
License: The MIT License (MIT)
